odeestimatorpy/__init__.py
odeestimatorpy/data_generator/__init__.py
odeestimatorpy/data_generator/generator.py
odeestimatorpy/data_generator/lambda_analyzer.py
odeestimatorpy/data_generator/ode_analyzer.py
odeestimatorpy/data_generator/ode_integrator.py
odeestimatorpy/data_generator/spline_cross_validator.py
odeestimatorpy/data_generator/spline_smoother.py
odeestimatorpy/data_generator/noise/__init__.py
odeestimatorpy/data_generator/noise/logarithmic_noise_generator.py
odeestimatorpy/data_generator/noise/noise_adder.py
odeestimatorpy/data_generator/noise/noise_generator.py
odeestimatorpy/data_generator/noise/normal_noise_generator.py
odeestimatorpy/data_generator/noise/uniform_noise_generator.py
odeestimatorpy/estimators/__init__.py
odeestimatorpy/estimators/estimator.py
odeestimatorpy/estimators/kkt_estimator.py
odeestimatorpy/estimators/pso_estimator.py
odeestimatorpy/experiments/__init__.py
odeestimatorpy/experiments/data_generation_pipeline.py
odeestimatorpy/experiments/kkt_experiment_pipeline.py
odeestimatorpy/experiments/pso_experiment_pipeline.py
odeestimatorpy/helpers/__init__.py
odeestimatorpy/helpers/clean_folders.py
odeestimatorpy/helpers/collect_models.py
odeestimatorpy/helpers/collect_parameters.py
odeestimatorpy/helpers/generators.py
odeestimatorpy/helpers/multiprocess.py
odeestimatorpy/helpers/resume_experiments.py
odeestimatorpy/helpers/save_to_json.py
odeestimatorpy/models/__init__.py
odeestimatorpy/models/linear_ode_model.py
odeestimatorpy/models/ode_model.py
odeestimatorpy/models/ode_model_base.py
odeestimatorpy/solvers/__init__.py
odeestimatorpy-2025.0.24.dist-info/LICENSE
odeestimatorpy-2025.0.24.dist-info/METADATA
odeestimatorpy-2025.0.24.dist-info/WHEEL
odeestimatorpy-2025.0.24.dist-info/top_level.txt
odeestimatorpy-2025.0.24.dist-info/RECORD
