Metadata-Version: 2.2
Name: odeestimatorpy
Version: 2025.0.24
Summary: ODE Estimator is a project designed to model and estimate parameters of systems of ordinary differential equations (ODEs).
Author-email: Nahomi Bouza <nahomi.bouza@gmail.com>
License: MIT License
Project-URL: Homepage, https://github.com/NahomiB/ode-estimator
Project-URL: Wiki, https://github.com/NahomiB/ode-estimator/wiki
Classifier: Programming Language :: Python :: 3
Classifier: Operating System :: OS Independent
Requires-Python: >=3.8
License-File: LICENSE
Requires-Dist: PyYAML>=6.0.2
Requires-Dist: matplotlib>=3.10.0
Requires-Dist: sympy>=1.13.3
Requires-Dist: numpy>=2.2.2
Requires-Dist: scipy>=1.15.1
Requires-Dist: tqdm>=4.67.1
Requires-Dist: seaborn>=0.13.2
Requires-Dist: scikit-learn>=1.6.1
Requires-Dist: pyswarms>=1.3.0
Requires-Dist: psutil>=6.1.1
